rag_assistant/.gitignore
rag_assistant/RagAssistant.py
rag_assistant/__init__.py
rag_assistant/config.json
rag_assistant/config.yaml
rag_assistant/favicon-32x32.png
rag_assistant/gradio_tabs/chat_tab.py
rag_assistant/gradio_tabs/document_edits_tab.py
rag_assistant/gradio_tabs/document_tab.py
rag_assistant/gradio_ui.py
rag_assistant/main.py
rag_assistant/template/config_template.json
rag_assistant/utils/configure.py
rag_assistant-0.2.4.dist-info/METADATA
rag_assistant-0.2.4.dist-info/WHEEL
rag_assistant-0.2.4.dist-info/entry_points.txt
rag_assistant-0.2.4.dist-info/RECORD
