Metadata-Version: 2.1
Name: rag_assistant
Version: 0.2.4
Summary: This repository includes rag_assistant
Home-page: http://github.com/swarmauri/rag_assistant
License: Apache-2.0
Author: Jacob Stewart
Author-email: jacob@swarmauri.com
Requires-Python: >=3.10,<4.0
Classifier: License :: OSI Approved :: Apache Software License
Classifier: Programming Language :: Python :: 3
Classifier: Programming Language :: Python :: 3.10
Classifier: Programming Language :: Python :: 3.11
Classifier: Programming Language :: Python :: 3.12
Classifier: Programming Language :: Python :: 3.13
Requires-Dist: PyMuPDF
Requires-Dist: gradio (==5.1.0)
Requires-Dist: swarmauri (==0.5.0)
Project-URL: Repository, http://github.com/swarmauri/rag_assistant
